Lab1/alu.v
module alu(
  input  [7:0] A,
  input  [7:0] B,
  input  [3:0] OP,
  output reg [7:0] Y,
  output reg C,   // carry/borrow/bit wybity
  output reg Z,   // zero
  output reg P,   // parity (even)
  output reg V    // overflow (tylko dla ADD/SUB)
);
  reg [8:0] tmp;  // pomocnicze 9 bitów (na przeniesienie)

  always @* begin
    Y = 8'h00; C = 1'b0; V = 1'b0; 

    case (OP)
      4'h0: begin // ADD
        tmp = {1'b0,A} + {1'b0,B};
        Y = tmp[7:0]; C = tmp[8];
        V = (~(A[7]^B[7])) & (A[7]^Y[7]);
      end
      4'h1: begin // SUB = A-B
        tmp = {1'b0,A} + {1'b0,(~B+8'd1)};
        Y = tmp[7:0]; C = tmp[8];      // 1 = brak pożyczki
        V = (A[7]^B[7]) & (A[7]^Y[7]);
      end
      4'h2: Y = A & B;                 // AND
      4'h3: Y = A | B;                 // OR
      4'h4: Y = A ^ B;                 // XOR
      4'h5: Y = ~A;                    // NOT A
      4'h6: begin tmp={1'b0,A}+9'd1; Y=tmp[7:0]; C=tmp[8]; V=(~A[7])&Y[7]; end // INC
      4'h7: begin tmp={1'b0,A}+{9{1'b1}}; Y=tmp[7:0]; C=tmp[8]; V=A[7]&(~Y[7]); end // DEC
      4'h8: begin Y = A << 1; C = A[7]; end // SHL
      4'h9: begin Y = A >> 1; C = A[0]; end // SHR (log.)
      4'hA: begin Y = {A[6:0],A[7]}; C = A[7]; end // ROL
      4'hB: begin Y = {A[0],A[7:1]}; C = A[0]; end // ROR
      4'hC: Y = (A==B) ? 8'd1 : 8'd0; // CMPEQ
      4'hD: Y = (A<B)  ? 8'd1 : 8'd0; // CMPLT (bez znaku)
      4'hE: Y = (A<B) ? A : B;        // MIN
      4'hF: Y = (A<B) ? B : A;        // MAX
    endcase

    Z = (Y==8'h00);
    P = ~^Y; // even parity
  end
endmodule

Lab1/alu_tb.v
`timescale 1ns/1ps
module alu_tb;
  reg  [7:0] A, B;
  reg  [3:0] OP;
  wire [7:0] Y;
  wire C, Z, P, V;

  alu DUT(.A(A), .B(B), .OP(OP), .Y(Y), .C(C), .Z(Z), .P(P), .V(V));

  task show; begin
    #1 $display("t=%0t OP=%h  A=%h B=%h  | Y=%h  C=%b Z=%b P=%b V=%b",
                $time, OP, A, B, Y, C, Z, P, V);
  end endtask

  // awaryjne odcięcie po 100 µs, gdyby coś poszło nie tak
  initial begin
    #100_000 $display("WATCHDOG STOP"); $finish;
  end

  initial begin
  $dumpfile("dump.vcd");
  $dumpvars(2, alu_tb);
  $dumpvars(0, alu_tb.A, alu_tb.B, alu_tb.OP, alu_tb.Y, alu_tb.C, alu_tb.Z, alu_tb.P, alu_tb.V);


    A=8'd15; B=8'd7;

    OP=4'h0; show(); // ADD
    OP=4'h1; show(); // SUB
    OP=4'h2; show(); // AND
    OP=4'h3; show(); // OR
    OP=4'h4; show(); // XOR
    OP=4'h5; show(); // NOT A
    OP=4'h6; show(); // INC
    OP=4'h7; show(); // DEC
    OP=4'h8; show(); // SHL
    OP=4'h9; show(); // SHR
    OP=4'hA; show(); // ROL
    OP=4'hB; show(); // ROR
    OP=4'hC; show(); // CMPEQ
    OP=4'hD; show(); // CMPLT
    OP=4'hE; show(); // MIN
    OP=4'hF; show(); // MAX

    // dodatkowe kilka przypadków
    A=8'd200; B=8'd100; OP=4'h0; show(); // ADD (carry/overflow)
    OP=4'h1; show();                     // SUB
    A=8'd50;  B=8'd50;  OP=4'h1; show(); // SUB -> Z=1
    A=8'b1000_0001; B=0; OP=4'h8; show();// SHL
    OP=4'h9; show();                     // SHR

    $display("ALL DONE");
    #1 $finish; 
  end
endmodule

Lab1/dump.vcd
$date
	Mon Oct 27 08:59:52 2025
$end
$version
	Icarus Verilog
$end
$timescale
	1ps
$end
$scope module alu_tb $end
$var wire 1 ! Z $end
$var wire 8 " Y [7:0] $end
$var wire 1 # V $end
$var wire 1 $ P $end
$var wire 1 % C $end
$var reg 8 & A [7:0] $end
$var reg 8 ' B [7:0] $end
$var reg 4 ( OP [3:0] $end
$scope module DUT $end
$var wire 8 ) A [7:0] $end
$var wire 8 * B [7:0] $end
$var wire 4 + OP [3:0] $end
$var reg 1 % C $end
$var reg 1 $ P $end
$var reg 1 # V $end
$var reg 8 , Y [7:0] $end
$var reg 1 ! Z $end
$var reg 9 - tmp [8:0] $end
$upscope $end
$scope task show $end
$upscope $end
$upscope $end
$enddefinitions $end
$comment Show the parameter values. $end
$dumpall
$end
#0
$dumpvars
b10110 -
b10110 ,
b0 +
b111 *
b1111 )
b0 (
b111 '
b1111 &
0%
0$
0#
b10110 "
0!
$end
#1000
1%
b100001000 -
b1000 "
b1000 ,
b1 (
b1 +
#2000
0%
b111 "
b111 ,
b10 (
b10 +
#3000
1$
b1111 "
b1111 ,
b11 (
b11 +
#4000
0$
b1000 "
b1000 ,
b100 (
b100 +
#5000
1$
b11110000 "
b11110000 ,
b101 (
b101 +
#6000
0$
b10000 -
b10000 "
b10000 ,
b110 (
b110 +
#7000
b1110 -
b1110 "
b1110 ,
b111 (
b111 +
#8000
1$
b11110 "
b11110 ,
b1000 (
b1000 +
#9000
0$
1%
b111 "
b111 ,
b1001 (
b1001 +
#10000
1$
0%
b11110 "
b11110 ,
b1010 (
b1010 +
#11000
1%
b10000111 "
b10000111 ,
b1011 (
b1011 +
#12000
1!
0%
b0 "
b0 ,
b1100 (
b1100 +
#13000
b1101 (
b1101 +
#14000
0$
0!
b111 "
b111 ,
b1110 (
b1110 +
#15000
1$
b1111 "
b1111 ,
b1111 (
b1111 +
#16000
0$
1%
b100101100 -
b101100 "
b101100 ,
b0 (
b0 +
b1100100 '
b1100100 *
b11001000 &
b11001000 )
#17000
1#
b101100100 -
1%
b1100100 "
b1100100 ,
b1 (
b1 +
#18000
1$
1!
b100000000 -
0#
1%
b0 "
b0 ,
b110010 '
b110010 *
b110010 &
b110010 )
#19000
0$
0!
b10 "
b10 ,
1%
b1000 (
b1000 +
b0 '
b0 *
b10000001 &
b10000001 )
#20000
1%
b1000000 "
b1000000 ,
b1001 (
b1001 +
