Lab2/pssw307_counter.v
`timescale 1ns/1ps

module pssw307_counter (
    input  wire       clk,
    input  wire       rst_n,   
    input  wire       we,      
    output reg  [4:0] q        
);
    always @(posedge clk or negedge rst_n) begin
        if (!rst_n) begin
            q <= 5'd0;
        end else if (we == 1'b0) begin
            if (q == 5'd30) q <= 5'd0;
            else            q <= q + 5'd1;
        end else begin
            if (q >= 5'd2)       q <= q - 5'd2;
            else if (q == 5'd1)  q <= 5'd29; 
            else                 q <= 5'd30; 
    end
endmodule

Lab2/tb_pssw307_counter.v
`timescale 1ns/1ps

module tb_pssw307_counter;
  reg        clk;
  reg        rst_n;   
  reg        we;      
  wire [4:0] q;

  pssw307_counter dut (.clk(clk), .rst_n(rst_n), .we(we), .q(q));

  initial clk = 1'b0;
  always #5 clk = ~clk;

  initial begin
 
    $dumpfile("pssw307.vcd");
    $dumpvars(0, tb_pssw307_counter);
    $display(" we  q(dec) q(bin)");
    $monitor("  %0d    %2d     %05b", we, q, q);


    rst_n = 0; we = 0;
    #17; rst_n = 1;                 

    repeat (35) @(posedge clk);

    @(negedge clk) we = 1;
    repeat (10) @(posedge clk);

    rst_n = 0; #6; rst_n = 1;
    we = 0;                        
    repeat (12) @(posedge clk);

    @(negedge clk) we = 1;
    repeat (8) @(posedge clk);

    @(negedge clk) we = 0;
    repeat (10) @(posedge clk);

    rst_n = 0; #4; rst_n = 1;
    we = 0;
    repeat (10) @(posedge clk);

    $finish;
  end
endmodule

Lab2/pssw307.vcd
$date
	Sun Nov 16 21:57:13 2025
$end
$version
	Icarus Verilog
$end
$timescale
	1ps
$end
$scope module tb_pssw307_counter $end
$var wire 5 ! q [4:0] $end
$var reg 1 " clk $end
$var reg 1 # rst_n $end
$var reg 1 $ we $end
$scope module dut $end
$var wire 1 " clk $end
$var wire 1 # rst_n $end
$var wire 1 $ we $end
$var reg 5 % q [4:0] $end
$upscope $end
$upscope $end
$enddefinitions $end
$comment Show the parameter values. $end
$dumpall
$end
#0
$dumpvars
b0 %
0$
0#
0"
b0 !
$end
#5000
1"
#10000
0"
#15000
1"
#17000
1#
#20000
0"
#25000
b1 !
b1 %
1"
#30000
0"
#35000
b10 !
b10 %
1"
#40000
0"
#45000
b11 !
b11 %
1"
#50000
0"
#55000
b100 !
b100 %
1"
#60000
0"
#65000
b101 !
b101 %
1"
#70000
0"
#75000
b110 !
b110 %
1"
#80000
0"
#85000
b111 !
b111 %
1"
#90000
0"
#95000
b1000 !
b1000 %
1"
#100000
0"
#105000
b1001 !
b1001 %
1"
#110000
0"
#115000
b1010 !
b1010 %
1"
#120000
0"
#125000
b1011 !
b1011 %
1"
#130000
0"
#135000
b1100 !
b1100 %
1"
#140000
0"
#145000
b1101 !
b1101 %
1"
#150000
0"
#155000
b1110 !
b1110 %
1"
#160000
0"
#165000
b1111 !
b1111 %
1"
#170000
0"
#175000
b10000 !
b10000 %
1"
#180000
0"
#185000
b10001 !
b10001 %
1"
#190000
0"
#195000
b10010 !
b10010 %
1"
#200000
0"
#205000
b10011 !
b10011 %
1"
#210000
0"
#215000
b10100 !
b10100 %
1"
#220000
0"
#225000
b10101 !
b10101 %
1"
#230000
0"
#235000
b10110 !
b10110 %
1"
#240000
0"
#245000
b10111 !
b10111 %
1"
#250000
0"
#255000
b11000 !
b11000 %
1"
#260000
0"
#265000
b11001 !
b11001 %
1"
#270000
0"
#275000
b11010 !
b11010 %
1"
#280000
0"
#285000
b11011 !
b11011 %
1"
#290000
0"
#295000
b11100 !
b11100 %
1"
#300000
0"
#305000
b11101 !
b11101 %
1"
#310000
0"
#315000
b11110 !
b11110 %
1"
#320000
0"
#325000
b0 !
b0 %
1"
#330000
0"
#335000
b1 !
b1 %
1"
#340000
0"
#345000
b10 !
b10 %
1"
#350000
0"
#355000
b11 !
b11 %
1"
#360000
0"
#365000
b100 !
b100 %
1"
#370000
1$
0"
#375000
b10 !
b10 %
1"
#380000
0"
#385000
b0 !
b0 %
1"
#390000
0"
#395000
b11110 !
b11110 %
1"
#400000
0"
#405000
b11100 !
b11100 %
1"
#410000
0"
#415000
b11010 !
b11010 %
1"
#420000
0"
#425000
b11000 !
b11000 %
1"
#430000
0"
#435000
b10110 !
b10110 %
1"
#440000
0"
#445000
b10100 !
b10100 %
1"
#450000
0"
#455000
b10010 !
b10010 %
1"
#460000
0"
#465000
b0 !
b0 %
0#
1"
#470000
0"
#471000
0$
1#
#475000
b1 !
b1 %
1"
#480000
0"
#485000
b10 !
b10 %
1"
#490000
0"
#495000
b11 !
b11 %
1"
#500000
0"
#505000
b100 !
b100 %
1"
#510000
0"
#515000
b101 !
b101 %
1"
#520000
0"
#525000
b110 !
b110 %
1"
#530000
0"
#535000
b111 !
b111 %
1"
#540000
0"
#545000
b1000 !
b1000 %
1"
#550000
0"
#555000
b1001 !
b1001 %
1"
#560000
0"
#565000
b1010 !
b1010 %
1"
#570000
0"
#575000
b1011 !
b1011 %
1"
#580000
0"
#585000
b1100 !
b1100 %
1"
#590000
1$
0"
#595000
b1010 !
b1010 %
1"
#600000
0"
#605000
b1000 !
b1000 %
1"
#610000
0"
#615000
b110 !
b110 %
1"
#620000
0"
#625000
b100 !
b100 %
1"
#630000
0"
#635000
b10 !
b10 %
1"
#640000
0"
#645000
b0 !
b0 %
1"
#650000
0"
#655000
b11110 !
b11110 %
1"
#660000
0"
#665000
b11100 !
b11100 %
1"
#670000
0$
0"
#675000
b11101 !
b11101 %
1"
#680000
0"
#685000
b11110 !
b11110 %
1"
#690000
0"
#695000
b0 !
b0 %
1"
#700000
0"
#705000
b1 !
b1 %
1"
#710000
0"
#715000
b10 !
b10 %
1"
#720000
0"
#725000
b11 !
b11 %
1"
#730000
0"
#735000
b100 !
b100 %
1"
#740000
0"
#745000
b101 !
b101 %
1"
#750000
0"
#755000
b110 !
b110 %
1"
#760000
0"
#765000
b0 !
b0 %
0#
1"
#769000
1#
#770000
0"
#775000
b1 !
b1 %
1"
#780000
0"
#785000
b10 !
b10 %
1"
#790000
0"
#795000
b11 !
b11 %
1"
#800000
0"
#805000
b100 !
b100 %
1"
#810000
0"
#815000
b101 !
b101 %
1"
#820000
0"
#825000
b110 !
b110 %
1"
#830000
0"
#835000
b111 !
b111 %
1"
#840000
0"
#845000
b1000 !
b1000 %
1"
#850000
0"
#855000
b1001 !
b1001 %
1"
#860000
0"
#865000
b1010 !
b1010 %
1"
